flask_jsontools/__init__.py
flask_jsontools/decorators.py
flask_jsontools/formatting.py
flask_jsontools/response.py
flask_jsontools/testing.py
flask_jsontools/views.py
flask_jsontools_slippers-0.1.6.dist-info/DESCRIPTION.rst
flask_jsontools_slippers-0.1.6.dist-info/METADATA
flask_jsontools_slippers-0.1.6.dist-info/RECORD
flask_jsontools_slippers-0.1.6.dist-info/WHEEL
flask_jsontools_slippers-0.1.6.dist-info/metadata.json
flask_jsontools_slippers-0.1.6.dist-info/top_level.txt
tests/__init__.py
tests/test_jsonapi.py
tests/test_methodview.py
tests/test_sqlalchemy.py
