Metadata-Version: 2.0
Name: flask-jsontools-slippers
Version: 0.1.6
Summary: JSON API tools for Flask 
Home-page: https://github.com/slippers/py-flask-jsontools
Author: Mark Vartanyan
Author-email: kolypto@gmail.com
License: BSD
Keywords: flask,json,sqlalchemy
Platform: any
Classifier: Development Status :: 5 - Production/Stable
Classifier: Intended Audience :: Developers
Classifier: Natural Language :: English
Classifier: Operating System :: OS Independent
Classifier: Programming Language :: Python :: 2
Classifier: Programming Language :: Python :: 3
Classifier: Topic :: Software Development :: Libraries :: Python Modules
Requires-Dist: click (==6.7)
Requires-Dist: flask (==0.12.1)
Requires-Dist: itsdangerous (==0.24)
Requires-Dist: jinja2 (==2.9.6)
Requires-Dist: markupsafe (==1.0)
Requires-Dist: werkzeug (==0.12.1)
